string_utils/__init__.py
string_utils/utils.py
string_utils_practice-0.1.dist-info/LICENSE
string_utils_practice-0.1.dist-info/METADATA
string_utils_practice-0.1.dist-info/WHEEL
string_utils_practice-0.1.dist-info/top_level.txt
string_utils_practice-0.1.dist-info/RECORD
